sids/__init__.py
sids/cli.py
sids/core.py
sids/adapters/fastapi_adapter.py
sids/adapters/flask_adapter.py
sids/adapters/jupyter_adapter.py
sids/adapters/tkinter_adapter.py
sids/components/__init__.py
sids/static/css/tailwind.css
sids/templates/base.html
sids-0.1.0.dist-info/licenses/LICENSE
sids-0.1.0.dist-info/METADATA
sids-0.1.0.dist-info/WHEEL
sids-0.1.0.dist-info/entry_points.txt
sids-0.1.0.dist-info/top_level.txt
sids-0.1.0.dist-info/RECORD
