Metadata-Version: 2.4
Name: sids
Version: 0.1.0
Summary: Selective Interface Design System: TailwindCSS + Python for universal GUIs
Author-email: SIDS Contributors <contact@example.com>
License: MIT
Project-URL: Homepage, https://github.com/yourusername/sids
Project-URL: Repository, https://github.com/yourusername/sids
Project-URL: Issues, https://github.com/yourusername/sids/issues
Keywords: gui,ui,tailwindcss,interface,framework
Classifier: Development Status :: 3 - Alpha
Classifier: Intended Audience :: Developers
Classifier: License :: OSI Approved :: MIT License
Classifier: Programming Language :: Python :: 3
Classifier: Programming Language :: Python :: 3.8
Classifier: Programming Language :: Python :: 3.9
Classifier: Programming Language :: Python :: 3.10
Classifier: Programming Language :: Python :: 3.11
Classifier: Programming Language :: Python :: 3.12
Classifier: Topic :: Software Development :: User Interfaces
Classifier: Topic :: Software Development :: Libraries :: Python Modules
Requires-Python: >=3.8
License-File: LICENSE
Requires-Dist: jinja2>=3.0.0
Requires-Dist: flask>=2.0.0
Provides-Extra: fastapi
Requires-Dist: fastapi>=0.68.0; extra == "fastapi"
Requires-Dist: uvicorn>=0.15.0; extra == "fastapi"
Provides-Extra: jupyter
Requires-Dist: ipython>=7.0.0; extra == "jupyter"
Requires-Dist: ipywidgets>=7.0.0; extra == "jupyter"
Provides-Extra: tkinter
Provides-Extra: dev
Requires-Dist: pytest>=6.0; extra == "dev"
Requires-Dist: black; extra == "dev"
Requires-Dist: flake8; extra == "dev"
Requires-Dist: mypy; extra == "dev"
Provides-Extra: all
Requires-Dist: fastapi>=0.68.0; extra == "all"
Requires-Dist: uvicorn>=0.15.0; extra == "all"
Requires-Dist: ipython>=7.0.0; extra == "all"
Requires-Dist: ipywidgets>=7.0.0; extra == "all"
Dynamic: license-file
